{"cameraMode":{"drawMode":0,"name":"Shaded","section":"Shading Mode"},"sceneLighting":true,"audioPlay":false,"sceneViewState":{"m_AlwaysRefresh":false,"showFog":true,"showSkybox":true,"showFlares":true,"showImageEffects":true,"showParticleSystems":true,"showVisualEffectGraphs":true,"m_FxEnabled":true},"in2DMode":false,"pivot":{"x":-9.101497650146485,"y":4.378262996673584,"z":2.765470504760742},"rotation":{"x":0.04087744653224945,"y":-0.34069737792015078,"z":0.014836433343589306,"w":0.9391716718673706},"size":7.108295917510986,"orthographic":false}